[
  {
    "_type": "robe",
    "nom": "Cape de tromperie",
    "unique_neerya": false,
    "force_req": 0,
    "endurance_req": 16,
    "dexterite_req": 0,
    "intelligence_req": 78,
    "sagesse_req": 15,
    "armure": 6.0,
    "prix": 0,
    "prix_detail": null,
    "informations": "Couleur: noire  \n+10 puissance nécromancie  \n+15 intelligence  \n-25 esquive",
    "obtention": "Jarko le nécromancien (Monts Righul, AR)"
  },
  {
    "_type": "robe",
    "nom": "Costume arcanique",
    "unique_neerya": true,
    "force_req": 0,
    "endurance_req": 0,
    "dexterite_req": 0,
    "intelligence_req": 75,
    "sagesse_req": 20,
    "armure": 4.0,
    "prix": 0,
    "prix_detail": null,
    "informations": "Couleur: noire  \n+5 puissance nécromancie  \n+20 intelligence  \n-10 esquive",
    "obtention": "Mage spectral (Arakas)"
  },
  {
    "_type": "robe",
    "nom": "Costume des marées",
    "unique_neerya": true,
    "force_req": 0,
    "endurance_req": 0,
    "dexterite_req": 0,
    "intelligence_req": 65,
    "sagesse_req": 20,
    "armure": 4.0,
    "prix": 0,
    "prix_detail": null,
    "informations": "Couleur: bleue foncée  \n+5 puissance eau  \n+15 intelligence  \n-10 esquive",
    "obtention": "Kraanian Nellas (Arakas)"
  },
  {
    "_type": "robe",
    "nom": "Manteau de la fournaise",
    "unique_neerya": true,
    "force_req": 0,
    "endurance_req": 0,
    "dexterite_req": 0,
    "intelligence_req": 65,
    "sagesse_req": 20,
    "armure": 4.0,
    "prix": 0,
    "prix_detail": null,
    "informations": "Couleur: noire  \n+5 puissance feu  \n+15 intelligence  \n-10 esquive",
    "obtention": "Thaumaturge Gobelin (Camp gobelin, AR)"
  },
  {
    "_type": "robe",
    "nom": "Manteau des vents",
    "unique_neerya": true,
    "force_req": 0,
    "endurance_req": 0,
    "dexterite_req": 0,
    "intelligence_req": 55,
    "sagesse_req": 55,
    "armure": 4.0,
    "prix": 0,
    "prix_detail": null,
    "informations": "Couleur: verte  \n+5 puissance air  \n+10 intelligence  \n+10 sagesse  \n-10 esquive",
    "obtention": "Enchanteur Orc (Arakas)"
  },
  {
    "_type": "robe",
    "nom": "Manteau du soleil",
    "unique_neerya": true,
    "force_req": 0,
    "endurance_req": 0,
    "dexterite_req": 0,
    "intelligence_req": 20,
    "sagesse_req": 75,
    "armure": 4.0,
    "prix": 0,
    "prix_detail": null,
    "informations": "Couleur: blanche  \n+5 puissance lumière  \n+20 sagesse  \n-10 esquive",
    "obtention": "Enchanteur Orc (Arakas)"
  },
  {
    "_type": "robe",
    "nom": "Robe blanche brillante",
    "unique_neerya": false,
    "force_req": 0,
    "endurance_req": 12,
    "dexterite_req": 0,
    "intelligence_req": 20,
    "sagesse_req": 35,
    "armure": 2.0,
    "prix": 0,
    "prix_detail": null,
    "informations": "Couleur: blanche  \n+5 sagesse  \n+5 force  \n-25 esquive",
    "obtention": "Pilleur de tombe (Arakas) Infirmières psychotiques/Fous (L'Asile, AR)"
  },
  {
    "_type": "robe",
    "nom": "Robe de glaise ancestrale",
    "unique_neerya": true,
    "force_req": 0,
    "endurance_req": 0,
    "dexterite_req": 0,
    "intelligence_req": 20,
    "sagesse_req": 65,
    "armure": 4.0,
    "prix": 0,
    "prix_detail": null,
    "informations": "Couleur: verte  \n+5 puissance terre  \n+15 sagesse  \n-10 esquive",
    "obtention": "Kraanian Nellas (Arakas)"
  },
  {
    "_type": "robe",
    "nom": "Robe des bois",
    "unique_neerya": false,
    "force_req": 0,
    "endurance_req": 12,
    "dexterite_req": 0,
    "intelligence_req": 28,
    "sagesse_req": 28,
    "armure": 2.0,
    "prix": 0,
    "prix_detail": null,
    "informations": "Couleur: verte  \n+5 intelligence  \n+5 sagesse  \n-25 esquive",
    "obtention": "Shamans orques (Arakas)"
  },
  {
    "_type": "robe",
    "nom": "Robe noire flottante",
    "unique_neerya": false,
    "force_req": 0,
    "endurance_req": 12,
    "dexterite_req": 0,
    "intelligence_req": 40,
    "sagesse_req": 15,
    "armure": 2.0,
    "prix": 0,
    "prix_detail": null,
    "informations": "Couleur: noire  \n+10 intelligence  \n-25 esquive",
    "obtention": "Balork (Arakas)"
  },
  {
    "_type": "robe",
    "nom": "Costume des morts",
    "unique_neerya": false,
    "force_req": 0,
    "endurance_req": 21,
    "dexterite_req": 0,
    "intelligence_req": 128,
    "sagesse_req": 15,
    "armure": 11.0,
    "prix": 0,
    "prix_detail": null,
    "informations": "Couleur: noire  \n+25 puissance nécromancie  \n+20 intelligence  \n-25 esquive",
    "obtention": "Sorciers Squelettes (Crypte - Raven's Dust)"
  },
  {
    "_type": "robe",
    "nom": "Habit de feuilles",
    "unique_neerya": false,
    "force_req": 0,
    "endurance_req": 20,
    "dexterite_req": 0,
    "intelligence_req": 15,
    "sagesse_req": 115,
    "armure": 10.0,
    "prix": 0,
    "prix_detail": null,
    "informations": "Couleur: verte  \n+40 sagesse  \n-25 esquive",
    "obtention": "<a href=\"https://www.t4c-neerya.com/wiki/quetes/ravens_dust/autres/habit_de_feuilles\" class=\"wikilink1\" title=\"quetes:ravens_dust:autres:habit_de_feuilles\" data-wiki-id=\"quetes:ravens_dust:autres:habit_de_feuilles\">Quête de l'Habit de Feuilles</a> (Raven's Dust)"
  },
  {
    "_type": "robe",
    "nom": "Manteau de la pluie",
    "unique_neerya": false,
    "force_req": 0,
    "endurance_req": 20,
    "dexterite_req": 0,
    "intelligence_req": 100,
    "sagesse_req": 20,
    "armure": 10.0,
    "prix": 0,
    "prix_detail": null,
    "informations": "Couleur: verte  \n+1 puissance eau et résistance eau par goutte de pluie dans votre inventaire. \nBonus des gouttes plafonné à 25 et coûte une goutte à chaque activation.  \nDurée: 5 secondes + 5 secondes par gemme dans votre inventaire.  \n \n-25 esquive",
    "obtention": "Araignée voleuse de vie (Forêt de non retour - Raven's Dust) Coffres Forêt de non retour (Raven's Dust)"
  },
  {
    "_type": "robe",
    "nom": "Manteau de prestidigitateur",
    "unique_neerya": false,
    "force_req": 0,
    "endurance_req": 20,
    "dexterite_req": 0,
    "intelligence_req": 110,
    "sagesse_req": 20,
    "armure": 10.0,
    "prix": 0,
    "prix_detail": null,
    "informations": "Couleur: noire  \n+10 puissance feu  \n+10 puissance eau  \n+20 intelligence  \n-25 esquive",
    "obtention": "Illusionnites (Raven's Dust)"
  },
  {
    "_type": "robe",
    "nom": "Manteau du crâne",
    "unique_neerya": false,
    "force_req": 0,
    "endurance_req": 30,
    "dexterite_req": 0,
    "intelligence_req": 100,
    "sagesse_req": 50,
    "armure": 30.0,
    "prix": 0,
    "prix_detail": null,
    "informations": "Couleur: noire  \n-30 esquive",
    "obtention": "Mystiques (Forêt de non retour)"
  },
  {
    "_type": "robe",
    "nom": "Manteau du sagittaire",
    "unique_neerya": true,
    "force_req": 0,
    "endurance_req": 0,
    "dexterite_req": 0,
    "intelligence_req": 0,
    "sagesse_req": 0,
    "armure": 6.0,
    "prix": 0,
    "prix_detail": null,
    "informations": "Couleur: brune  \n+30 archerie  \n+5 résistance terre  \n-20 esquive  \n \n<strong>+3% de chance d'activer en attaquant un sort augmentant la dextérité de 4% pendant 1 minute</strong>",
    "obtention": "<a href=\"https://www.t4c-neerya.com/wiki/quetes/ravens_dust/autres/manteau_du_sagittaire\" class=\"wikilink1\" title=\"quetes:ravens_dust:autres:manteau_du_sagittaire\" data-wiki-id=\"quetes:ravens_dust:autres:manteau_du_sagittaire\">Quête du Manteau du Sagittaire</a> (Raven's Dust)"
  },
  {
    "_type": "robe",
    "nom": "Robe de Drachen",
    "unique_neerya": false,
    "force_req": 0,
    "endurance_req": 25,
    "dexterite_req": 0,
    "intelligence_req": 98,
    "sagesse_req": 73,
    "armure": 15.0,
    "prix": 0,
    "prix_detail": null,
    "informations": "Couleur: noire  \n+10 toutes puissances  \n+1 toute puissances par gemme des étoiles dans votre inventaire  \n+5 méditation par gemme des étoiles dans votre inventaire  \nDurée: 5 secondes + 5 secondes par gemme dans votre inventaire.  \nEffet des gemmes cap à 25.",
    "obtention": "Araignée voleuse de vie (Forêt de non retour)"
  },
  {
    "_type": "robe",
    "nom": "Robe de protection ornée de runes",
    "unique_neerya": false,
    "force_req": 0,
    "endurance_req": 16,
    "dexterite_req": 0,
    "intelligence_req": 43,
    "sagesse_req": 50,
    "armure": 11.0,
    "prix": 0,
    "prix_detail": null,
    "informations": "Couleur: verte  \n+5 force  \n+5 intelligence  \n+5 sagesse  \n-25 esquive",
    "obtention": "Shamans minotaures (Labyrinthe des minotaures - Raven's Dust)"
  },
  {
    "_type": "robe",
    "nom": "Robe des elfes en soie d'argent",
    "unique_neerya": false,
    "force_req": 0,
    "endurance_req": 25,
    "dexterite_req": 0,
    "intelligence_req": 20,
    "sagesse_req": 73,
    "armure": 6.0,
    "prix": 0,
    "prix_detail": null,
    "informations": "Couleur: blanche  \n+10 sagesse  \n+5 force  \n+10 résistance nécromancie  \n-16 esquive",
    "obtention": "Golem de chair (Tour de Zhakar, RD)"
  },
  {
    "_type": "robe",
    "nom": "Tissu taché de cendres et de sang",
    "unique_neerya": true,
    "force_req": 0,
    "endurance_req": 16,
    "dexterite_req": 0,
    "intelligence_req": 43,
    "sagesse_req": 50,
    "armure": 11.0,
    "prix": 0,
    "prix_detail": null,
    "informations": "+5 force  \n+5 intelligence  \n+5 sagesse",
    "obtention": "Raven's Dust??? Non lootable sur un monstre (confirmé par staff)"
  },
  {
    "_type": "robe",
    "nom": "Cape d'Armagueddon",
    "unique_neerya": false,
    "force_req": 0,
    "endurance_req": 37,
    "dexterite_req": 0,
    "intelligence_req": 175,
    "sagesse_req": 70,
    "armure": 20.0,
    "prix": 0,
    "prix_detail": null,
    "informations": "Couleur: noire  \n+50 intelligence  \n-25 esquive  \n \n<strong>Lance parfois un sort type météorite mono-cible lorsque le porteur est touché</strong>",
    "obtention": "<a href=\"https://www.t4c-neerya.com/wiki/quetes/stoneheim/karma/mordenthal\" class=\"wikilink1\" title=\"quetes:stoneheim:karma:mordenthal\" data-wiki-id=\"quetes:stoneheim:karma:mordenthal\">Quête de Mordenthal</a> (SH)"
  },
  {
    "_type": "robe",
    "nom": "Manteau d'émeraude \n(Prêtre terre)",
    "unique_neerya": true,
    "force_req": 0,
    "endurance_req": 25,
    "dexterite_req": 0,
    "intelligence_req": 20,
    "sagesse_req": 185,
    "armure": 18.0,
    "prix": 0,
    "prix_detail": null,
    "informations": "Couleur: blanche  \n+20 puissance terre  \n+40 sagesse  \n-25 esquive",
    "obtention": "Coffres (Zone Oracle, SH)"
  },
  {
    "_type": "robe",
    "nom": "Manteau de l'archer",
    "unique_neerya": false,
    "force_req": 25,
    "endurance_req": 0,
    "dexterite_req": 70,
    "intelligence_req": 30,
    "sagesse_req": 40,
    "armure": 10.0,
    "prix": 0,
    "prix_detail": null,
    "informations": "Couleur: noire  \n+50 archerie  \n+25 esquive",
    "obtention": "<a href=\"https://www.t4c-neerya.com/wiki/quetes/stoneheim/autres/manteau_de_l_archer\" class=\"wikilink1\" title=\"quetes:stoneheim:autres:manteau_de_l_archer\" data-wiki-id=\"quetes:stoneheim:autres:manteau_de_l_archer\">Quête du Manteau de l'Archer</a> (Stonecrest, SH)"
  },
  {
    "_type": "robe",
    "nom": "Manteau de la mort \n(Nécromancien)",
    "unique_neerya": false,
    "force_req": 0,
    "endurance_req": 25,
    "dexterite_req": 0,
    "intelligence_req": 201,
    "sagesse_req": 15,
    "armure": 15.0,
    "prix": 0,
    "prix_detail": null,
    "informations": "Couleur: noire  \n+20 puisance nécromancie  \n+40 intelligence  \n-25 esquive  \n \n<strong>Lance parfois un sort d'affaiblissement sur l'ennemi lorsque le porteur est touché</strong> \n(8-16 points de dégâts sur la durée pendant 20 secondes, affectés par la résistance à la nécromancie de l'ennemi)",
    "obtention": "Coffres (Zone Oracle, SH)"
  },
  {
    "_type": "robe",
    "nom": "Manteau des océans \n(Mage eau)",
    "unique_neerya": true,
    "force_req": 0,
    "endurance_req": 20,
    "dexterite_req": 0,
    "intelligence_req": 200,
    "sagesse_req": 10,
    "armure": 16.0,
    "prix": 0,
    "prix_detail": null,
    "informations": "Couleur: bleue claire  \n+20 puissance eau  \n+50 intelligence  \n-25 esquive",
    "obtention": "Coffres (Zone Oracle, SH)"
  },
  {
    "_type": "robe",
    "nom": "Manteau du chaman",
    "unique_neerya": false,
    "force_req": 0,
    "endurance_req": 18,
    "dexterite_req": 0,
    "intelligence_req": 50,
    "sagesse_req": 68,
    "armure": 8.0,
    "prix": 0,
    "prix_detail": null,
    "informations": "Couleur: verte  \n+10 force  \n+10 intelligence  \n+15 sagesse  \n-25 esquive",
    "obtention": "Grott/Ghundarg Garak (Raven's Dust) Corps de skraug (Cavernes des skaugs, SH)"
  },
  {
    "_type": "robe",
    "nom": "Manteau du renouveau \n(Mage / Prêtre)",
    "unique_neerya": false,
    "force_req": 0,
    "endurance_req": 25,
    "dexterite_req": 0,
    "intelligence_req": 106,
    "sagesse_req": 112,
    "armure": 15.0,
    "prix": 0,
    "prix_detail": null,
    "informations": "Couleur: verte  \n+25 intelligence  \n+25 sagesse  \n+10 force  \n-25 esquive  \n \n<strong>Lance parfois le sort Renouveau lorsque le porteur est touché</strong>  \n(Régénération rapide des points de mana pendant 15 secondes)",
    "obtention": "Coffres (Zone Oracle, SH)"
  },
  {
    "_type": "robe",
    "nom": "Robe céleste",
    "unique_neerya": false,
    "force_req": 0,
    "endurance_req": 28,
    "dexterite_req": 0,
    "intelligence_req": 73,
    "sagesse_req": 135,
    "armure": 18.0,
    "prix": 0,
    "prix_detail": null,
    "informations": "Couleur: blanche  \n+25 sagesse  \n+10 toutes résistances  \n-25 esquive",
    "obtention": "<a href=\"https://www.t4c-neerya.com/wiki/quetes/stoneheim/autres/robe_celeste\" class=\"wikilink1\" title=\"quetes:stoneheim:autres:robe_celeste\" data-wiki-id=\"quetes:stoneheim:autres:robe_celeste\">Quête de la Robe Céleste</a> (Iles éthérées, SH)"
  },
  {
    "_type": "robe",
    "nom": "Robe d'ArchMagi \n(Mage feu)",
    "unique_neerya": false,
    "force_req": 0,
    "endurance_req": 27,
    "dexterite_req": 0,
    "intelligence_req": 190,
    "sagesse_req": 15,
    "armure": 17.0,
    "prix": 0,
    "prix_detail": null,
    "informations": "Couleur: rouge  \n+20 puissance feu  \n+50 intelligence \n-25 esquive",
    "obtention": "Coffres (Zone Oracle, SH)"
  },
  {
    "_type": "robe",
    "nom": "Robe de grand prêtre \n(Prêtre lumière)",
    "unique_neerya": false,
    "force_req": 0,
    "endurance_req": 25,
    "dexterite_req": 0,
    "intelligence_req": 25,
    "sagesse_req": 155,
    "armure": 15.0,
    "prix": 0,
    "prix_detail": null,
    "informations": "Couleur: blanche  \n+20 puissance lumière  \n+10 sagesse  \n+10 endurance  \n-25 esquive",
    "obtention": "Coffres (Zone Oracle, SH)"
  },
  {
    "_type": "robe",
    "nom": "Robe des enfers",
    "unique_neerya": false,
    "force_req": 0,
    "endurance_req": 28,
    "dexterite_req": 0,
    "intelligence_req": 123,
    "sagesse_req": 85,
    "armure": 18.0,
    "prix": 0,
    "prix_detail": null,
    "informations": "Couleur: noire  \n+25 résistance feu  \n+25 résistance nécromancie  \n+25 intelligence  \n-15 puissance terre  \n-15 puissance lumière  \n-15 résistance eau  \n-25 esquive",
    "obtention": "<a href=\"https://www.t4c-neerya.com/wiki/quetes/stoneheim/autres/malachai\" class=\"wikilink1\" title=\"quetes:stoneheim:autres:malachai\" data-wiki-id=\"quetes:stoneheim:autres:malachai\">Quête de Malachai</a> (SH)"
  },
  {
    "_type": "robe",
    "nom": "Robe des âmes purifiées",
    "unique_neerya": false,
    "force_req": 0,
    "endurance_req": 18,
    "dexterite_req": 0,
    "intelligence_req": 15,
    "sagesse_req": 103,
    "armure": 8.0,
    "prix": 0,
    "prix_detail": null,
    "informations": "Couleur: blanche  \n+10 sagesse  \n+25 résistance nécromancie  \n-25 esquive",
    "obtention": "Purificateurs (Iles éthérées, SH)"
  },
  {
    "_type": "robe",
    "nom": "Robe du mistral \n(Prêtre air / Mage air)",
    "unique_neerya": true,
    "force_req": 0,
    "endurance_req": 20,
    "dexterite_req": 0,
    "intelligence_req": 105,
    "sagesse_req": 110,
    "armure": 17.0,
    "prix": 0,
    "prix_detail": null,
    "informations": "Couleur: blanche  \n+20 puissance air  \n+25 intelligence  \n+25 sagesse  \n-25 esquive",
    "obtention": "Coffres (Zone Oracle, SH)"
  },
  {
    "_type": "robe",
    "nom": "Bure du Moine",
    "unique_neerya": true,
    "force_req": 0,
    "endurance_req": 30,
    "dexterite_req": 0,
    "intelligence_req": 18,
    "sagesse_req": 250,
    "armure": 20.0,
    "prix": 0,
    "prix_detail": null,
    "informations": "Couleur: marron  \n+15 puissance air  \n+15 puissance terre  \n+25 sagesse  \n+10 intelligence  \n-25 esquive",
    "obtention": "<a href=\"https://www.t4c-neerya.com/wiki/quetes/grim_hawk/autres/chevalier_spectral\" class=\"wikilink1\" title=\"quetes:grim_hawk:autres:chevalier_spectral\" data-wiki-id=\"quetes:grim_hawk:autres:chevalier_spectral\">Quête du chevalier spectral (Rognar Mortes)</a> (Grim Hawk)"
  },
  {
    "_type": "robe",
    "nom": "Cape de damnation \n(Mage feu)",
    "unique_neerya": true,
    "force_req": 0,
    "endurance_req": 31,
    "dexterite_req": 0,
    "intelligence_req": 277,
    "sagesse_req": 15,
    "armure": 21.0,
    "prix": 0,
    "prix_detail": null,
    "informations": "Couleur: rouge  \n+10 puissance feu  \n+75 intelligence \n-25 esquive  \n \n<strong>Lance parfois un sort de zone à courte portée type dard de feu lorsque le porteur est touché (vise même les joueurs aux alentours)</strong>",
    "obtention": "<strong>Invocation GM</strong>"
  },
  {
    "_type": "robe",
    "nom": "Manteau des bénédictions infinies \n(Prêtre terre / lumière)",
    "unique_neerya": true,
    "force_req": 0,
    "endurance_req": 27,
    "dexterite_req": 0,
    "intelligence_req": 20,
    "sagesse_req": 355,
    "armure": 15.0,
    "prix": 0,
    "prix_detail": null,
    "informations": "Couleur: blanche  \n+15 puissance terre  \n+15 puissance lumière  \n+30 sagesse  \n-25 esquive",
    "obtention": "Assemblage de glaise (Grim Hawk)"
  },
  {
    "_type": "robe",
    "nom": "Manteau des bénédictions infinies parfait \n(Prêtre terre / lumière)",
    "unique_neerya": true,
    "force_req": 0,
    "endurance_req": 27,
    "dexterite_req": 0,
    "intelligence_req": 20,
    "sagesse_req": 355,
    "armure": 30.0,
    "prix": 0,
    "prix_detail": null,
    "informations": "Couleur: blanche  \n+25 puissance terre  \n+25 puissance lumière  \n+65 sagesse  \n-25 esquive",
    "obtention": "Assistant (Entrée instance AR) Prix : Manteau des bénédictions infinies 8 points d'instance AR HM"
  },
  {
    "_type": "robe",
    "nom": "Manteau des profondeurs de Grim Hawk",
    "unique_neerya": true,
    "force_req": 0,
    "endurance_req": 25,
    "dexterite_req": 0,
    "intelligence_req": 355,
    "sagesse_req": 25,
    "armure": 25.0,
    "prix": 0,
    "prix_detail": null,
    "informations": "Couleur: grise  \n+30 puissance nécromancie  \n+55 intelligence",
    "obtention": "Gjalpinulva (Dragon Renégat) (Grim Hawk)"
  },
  {
    "_type": "robe",
    "nom": "Robe d'Eos \n(Prêtre air / Mage air)",
    "unique_neerya": true,
    "force_req": 0,
    "endurance_req": 0,
    "dexterite_req": 0,
    "intelligence_req": 195,
    "sagesse_req": 190,
    "armure": 20.0,
    "prix": 0,
    "prix_detail": null,
    "informations": "Couleur: jaune  \n+15 puissance air  \n+20 intelligence  \n+20 sagesse  \n-25 esquive",
    "obtention": "Bouleau corrompu (Grim Hawk)"
  },
  {
    "_type": "robe",
    "nom": "Robe d'Eos parfaite \n(Prêtre air / Mage air)",
    "unique_neerya": true,
    "force_req": 0,
    "endurance_req": 0,
    "dexterite_req": 0,
    "intelligence_req": 195,
    "sagesse_req": 190,
    "armure": 30.0,
    "prix": 0,
    "prix_detail": null,
    "informations": "Couleur: jaune  \n+25 puissance air  \n+40 intelligence  \n+40 sagesse  \n-25 esquive",
    "obtention": "Assistant (Entrée instance AR) Prix : Robe d'Eos 8 points d'instance AR HM"
  },
  {
    "_type": "robe",
    "nom": "Robe des Âges \n(Mage feu / eau)",
    "unique_neerya": true,
    "force_req": 0,
    "endurance_req": 27,
    "dexterite_req": 0,
    "intelligence_req": 355,
    "sagesse_req": 20,
    "armure": 15.0,
    "prix": 0,
    "prix_detail": null,
    "informations": "<strong>Couleur: rouge ou bleue foncée</strong>  \n+15 puissance feu  \n+15 puissance eau  \n+30 intelligence  \n-25 esquive",
    "obtention": "Serpent Arcanique (Grim Hawk)"
  },
  {
    "_type": "robe",
    "nom": "Robe des Âges parfaite \n(Mage feu / eau)",
    "unique_neerya": true,
    "force_req": 0,
    "endurance_req": 27,
    "dexterite_req": 0,
    "intelligence_req": 355,
    "sagesse_req": 20,
    "armure": 30.0,
    "prix": 0,
    "prix_detail": null,
    "informations": "<strong>Couleur: rouge ou bleue foncée</strong>  \n+25 puissance feu  \n+25 puissance eau  \n+65 intelligence  \n-25 esquive",
    "obtention": "Assistant (Entrée instance AR) Prix : Robe des Âges 8 points d'instance AR HM"
  },
  {
    "_type": "robe",
    "nom": "Chandail rubis de Malkéas \n(Mage feu / eau)",
    "unique_neerya": true,
    "force_req": 0,
    "endurance_req": 27,
    "dexterite_req": 0,
    "intelligence_req": 450,
    "sagesse_req": 30,
    "armure": 28.0,
    "prix": 0,
    "prix_detail": null,
    "informations": "+30 puissance feu OU eau (suivant l'élément dominant du porteur)  \n+70 intelligence  \n+10 compétence Piller",
    "obtention": "Seigneur-Sorcier (Ebon Hold)"
  },
  {
    "_type": "robe",
    "nom": "Chandail rubis de Malkéas parfait \n(Mage feu / eau)",
    "unique_neerya": true,
    "force_req": 0,
    "endurance_req": 27,
    "dexterite_req": 0,
    "intelligence_req": 450,
    "sagesse_req": 30,
    "armure": 28.0,
    "prix": 0,
    "prix_detail": null,
    "informations": "+30 puissance feu  \n+30 puissance eau  \n+70 intelligence  \n+2 toutes résistances (+4 si le porteur à 200 endurance ou +)  \n+10 compétence Piller",
    "obtention": "Assistant (Entrée instance SH) Prix : Chandail rubis de Malkéas 5 points d'instance SH HM"
  },
  {
    "_type": "robe",
    "nom": "Tissage cérémonial du Roy Noir \n(Prêtre terre / lumière)",
    "unique_neerya": true,
    "force_req": 0,
    "endurance_req": 27,
    "dexterite_req": 0,
    "intelligence_req": 30,
    "sagesse_req": 450,
    "armure": 28.0,
    "prix": 0,
    "prix_detail": null,
    "informations": "Couleur: blanche avec épaulettes  \n+30 puissance terre OU lumière (suivant l'élément dominant du personnage)  \n+70 sagesse  \n+10 compétence Ramener à la vie  \n-30 esquive",
    "obtention": "Seigneur-Sorcier (Ebon Hold)"
  },
  {
    "_type": "robe",
    "nom": "Tissage cérémonial du Roy Noir parfait \n(Prêtre terre / lumière)",
    "unique_neerya": true,
    "force_req": 0,
    "endurance_req": 27,
    "dexterite_req": 0,
    "intelligence_req": 30,
    "sagesse_req": 450,
    "armure": 28.0,
    "prix": 0,
    "prix_detail": null,
    "informations": "Couleur: blanche avec épaulettes  \n+30 puissance terre  \n+30 puissance lumière  \n+70 sagesse  \n+10 compétence Ramener à la vie  \n+2 toutes résistances (+4 si le porteur à 200 endurance ou plus)  \n-30 esquive",
    "obtention": "Assistant (Entrée instance SH) Prix : Tissage Cérémonial du Roy noir 5 points d'instance SH HM"
  },
  {
    "_type": "robe",
    "nom": "Tunique du Néant du Seigneur-Sorcier \n(Mage feu / eau)",
    "unique_neerya": true,
    "force_req": 0,
    "endurance_req": 27,
    "dexterite_req": 0,
    "intelligence_req": 450,
    "sagesse_req": 30,
    "armure": 28.0,
    "prix": 0,
    "prix_detail": null,
    "informations": "+30 puissance feu OU eau (suivant l'élément dominant du porteur)  \n+70 intelligence  \n+10 compétence Piller",
    "obtention": "Seigneur-Sorcier (Ebon Hold) <strong>A vérifier si le loot est revenu</strong>"
  },
  {
    "_type": "robe",
    "nom": "Tunique du Néant du Seigneur-Sorcier parfaite \n(Mage feu / eau)",
    "unique_neerya": true,
    "force_req": 0,
    "endurance_req": 27,
    "dexterite_req": 0,
    "intelligence_req": 450,
    "sagesse_req": 30,
    "armure": 28.0,
    "prix": 0,
    "prix_detail": null,
    "informations": "+30 puissance feu  \n+30 puissance eau  \n+70 intelligence  \n+2 toutes résistances (+4 si le porteur à 200 endurance ou +)  \n+10 compétence Piller",
    "obtention": "Assistant (Entrée instance SH) Prix : Tunique du Néant du Seigneur-Sorcier 5 points d'instance SH HM"
  },
  {
    "_type": "robe",
    "nom": "Étoffe-éclair d'Eolia \n(Prêtre air / Mage air)",
    "unique_neerya": true,
    "force_req": 0,
    "endurance_req": 0,
    "dexterite_req": 0,
    "intelligence_req": 198,
    "sagesse_req": 290,
    "armure": 38.0,
    "prix": 0,
    "prix_detail": null,
    "informations": "Couleur: jaune avec épaulettes  \n+30 puissance air  \n+50 intelligence  \n+50 sagesse  \n-8 puissance feu  \n-8 puissance eau  \n-30 esquive",
    "obtention": "Seigneur-Sorcier (Ebon Hold)"
  },
  {
    "_type": "robe",
    "nom": "Étoffe-éclair d'Eolia parfaite \n(Prêtre air / Mage air)",
    "unique_neerya": true,
    "force_req": 0,
    "endurance_req": 0,
    "dexterite_req": 0,
    "intelligence_req": 198,
    "sagesse_req": 290,
    "armure": 38.0,
    "prix": 0,
    "prix_detail": null,
    "informations": "Couleur: jaune avec épaulettes  \n+30 puissance air  \n+50 intelligence  \n+50 sagesse  \n+2 toutes résistances (+4 si le porteur a 200 endurance ou plus)",
    "obtention": "Assistant (Entrée instance SH) Prix : Étoffe-éclair d'Eolia 5 points d'instance SH HM"
  },
  {
    "_type": "robe",
    "nom": "Toge d'Una",
    "unique_neerya": true,
    "force_req": 0,
    "endurance_req": 40,
    "dexterite_req": 0,
    "intelligence_req": 45,
    "sagesse_req": 356,
    "armure": 31.0,
    "prix": 0,
    "prix_detail": null,
    "informations": "+50 sagesse  \n+2 Chance  \n+5 toutes résistances",
    "obtention": "» Drop <em>coffre Una</em> (Tour blanche, ZE) » Drop <em>Les prisonniers du temps</em> (Boss 180+) » <em>Un artisan aventurier</em> (Côte des berserkers, DS)"
  },
  {
    "_type": "robe",
    "nom": "Toge d'Una aérienne \n(Prêtre air / Mage air)",
    "unique_neerya": true,
    "force_req": 0,
    "endurance_req": 40,
    "dexterite_req": 0,
    "intelligence_req": 447,
    "sagesse_req": 447,
    "armure": 31.0,
    "prix": 0,
    "prix_detail": null,
    "informations": "+45 puissance air  \n+60 sagesse  \n+60 intelligence  \n+5 toutes résistances  \n+2 chance",
    "obtention": "L'Arcaniste (Draconis Sanctum) Prix : Toge d'Una 8 000 000 pièces d'or 75 larmes de dragon 4 potion de focalisation"
  },
  {
    "_type": "robe",
    "nom": "Toge d'Una sainte \n(Prêtre tank)",
    "unique_neerya": true,
    "force_req": 0,
    "endurance_req": 165,
    "dexterite_req": 0,
    "intelligence_req": 40,
    "sagesse_req": 606,
    "armure": 41.0,
    "prix": 0,
    "prix_detail": null,
    "informations": "+40 puissance terre OU lumière OU air (suivant l'élément dominant du porteur) \n+80 sagesse \n+10 toutes résistances \n+10 compétence Ramener à la vie \n+2 chance",
    "obtention": "L'Arcaniste (Draconis Sanctum) Prix : Toge d'Una 8 000 000 pièces d'or 75 larmes de dragon 4 potion de focalisation"
  },
  {
    "_type": "robe",
    "nom": "Toge d'Una sanctifiée \n(Prêtre lumière)",
    "unique_neerya": true,
    "force_req": 0,
    "endurance_req": 40,
    "dexterite_req": 0,
    "intelligence_req": 40,
    "sagesse_req": 756,
    "armure": 31.0,
    "prix": 0,
    "prix_detail": null,
    "informations": "+45 puissance lumière  \n+90 sagesse  \n+5 toutes résistances  \n+15 compétence Ramener à la vie  \n+2 chance",
    "obtention": "L'Arcaniste (Draconis Sanctum) Prix : Toge d'Una 8 000 000 pièces d'or 75 larmes de dragon 4 potion de focalisation"
  },
  {
    "_type": "robe",
    "nom": "Toge d'Una tellurique \n(Prêtre terre)",
    "unique_neerya": true,
    "force_req": 0,
    "endurance_req": 40,
    "dexterite_req": 0,
    "intelligence_req": 40,
    "sagesse_req": 756,
    "armure": 31.0,
    "prix": 0,
    "prix_detail": null,
    "informations": "+45 puissance terre  \n+90 sagesse  \n+5 toutes résistances  \n+5 compétence Ramener à la vie  \n+2 chance",
    "obtention": "L'Arcaniste (Draconis Sanctum) Prix : Toge d'Una 8 000 000 pièces d'or 75 larmes de dragon 4 potion de focalisation"
  },
  {
    "_type": "robe",
    "nom": "Chaînes tissées de Saehrimni",
    "unique_neerya": true,
    "force_req": 0,
    "endurance_req": 40,
    "dexterite_req": 0,
    "intelligence_req": 427,
    "sagesse_req": 40,
    "armure": 31.0,
    "prix": 0,
    "prix_detail": null,
    "informations": "+50 intelligence  \n+5 toutes résistances  \n+2 chance",
    "obtention": "» Drop <em>coffre Una</em> (Tour blanche, ZE) » Drop <em>Les prisonniers du temps</em> (Boss 180+) » <em>Un artisan aventurier</em> (Côte des berserkers, DS)"
  },
  {
    "_type": "robe",
    "nom": "Chaînes tissées de Saehrimni corrompues \n(Nécromancien)",
    "unique_neerya": true,
    "force_req": 0,
    "endurance_req": 40,
    "dexterite_req": 0,
    "intelligence_req": 827,
    "sagesse_req": 40,
    "armure": 31.0,
    "prix": 0,
    "prix_detail": null,
    "informations": "+45 puissance nécro  \n+90 intelligence  \n+5 toutes résistances  \n+2 chance",
    "obtention": "L'Arcaniste (Draconis Sanctum) Prix : Chaînes tissées de Saehrimni 8 000 000 pièces d'or 75 larmes de dragon 4 potion de focalisation"
  },
  {
    "_type": "robe",
    "nom": "Chaînes tissées de Saehrimni enflammées \n(Mage feu)",
    "unique_neerya": true,
    "force_req": 0,
    "endurance_req": 40,
    "dexterite_req": 0,
    "intelligence_req": 827,
    "sagesse_req": 40,
    "armure": 31.0,
    "prix": 0,
    "prix_detail": null,
    "informations": "+45 puissance feu  \n+90 intelligence  \n+5 toutes résistances  \n+2 chance",
    "obtention": "L'Arcaniste (Draconis Sanctum) Prix : Chaînes tissées de Saehrimni 8 000 000 pièces d'or 75 larmes de dragon 4 potion de focalisation"
  },
  {
    "_type": "robe",
    "nom": "Chaînes tissées de Saehrimni glacées \n(Mage eau)",
    "unique_neerya": true,
    "force_req": 0,
    "endurance_req": 40,
    "dexterite_req": 0,
    "intelligence_req": 827,
    "sagesse_req": 40,
    "armure": 31.0,
    "prix": 0,
    "prix_detail": null,
    "informations": "+45 puissance eau  \n+90 intelligence  \n+5 toutes résistances  \n+2 chance",
    "obtention": "L'Arcaniste (Draconis Sanctum) Prix : Chaînes tissées de Saehrimni 8 000 000 pièces d'or 75 larmes de dragon 4 potion de focalisation"
  },
  {
    "_type": "robe",
    "nom": "Chaînes tissées de Saehrimni solides \n(Mage tank)",
    "unique_neerya": true,
    "force_req": 0,
    "endurance_req": 165,
    "dexterite_req": 0,
    "intelligence_req": 677,
    "sagesse_req": 40,
    "armure": 41.0,
    "prix": 0,
    "prix_detail": null,
    "informations": "+40 puissance feu OU eau OU air OU nécro (suivant l'élément dominant du porteur)  \n+80 intelligence  \n+10 toutes résistances  \n+2 chance",
    "obtention": "L'Arcaniste (Draconis Sanctum) Prix : Chaînes tissées de Saehrimni 8 000 000 pièces d'or 75 larmes de dragon 4 potion de focalisation"
  },
  {
    "_type": "robe",
    "nom": "Atours du roi barbare",
    "unique_neerya": true,
    "force_req": 100,
    "endurance_req": 50,
    "dexterite_req": 75,
    "intelligence_req": 100,
    "sagesse_req": 100,
    "armure": 21.0,
    "prix": 0,
    "prix_detail": null,
    "informations": "+10 force  \n+10 dextérité  \n+10 intelligence  \n+10 sagesse  \n+5 toutes résistances  \n+25 archerie  \n+25 attaque",
    "obtention": "» Drop <em>coffre Una</em> (Tour blanche, ZE) » Drop <em>Les prisonniers du temps</em> (Boss 180+) » <em>Un artisan aventurier</em> (Côte des berserkers, DS)"
  },
  {
    "_type": "robe",
    "nom": "Atours du roi barbare d'innervation \n(Archer-Mage air)",
    "unique_neerya": true,
    "force_req": 0,
    "endurance_req": 40,
    "dexterite_req": 417,
    "intelligence_req": 220,
    "sagesse_req": 220,
    "armure": 21.0,
    "prix": 0,
    "prix_detail": null,
    "informations": "+30 puissance air  \n+5 résistance feu, eau, air, terre, nécro  \n+50 dextérité  \n+25 intelligence  \n+25 sagesse  \n+100 compétence Archerie",
    "obtention": "L'Arcaniste (Draconis Sanctum) Prix : Atours du roi barbare 6 400 000 pièces d'or 60 larmes de dragon 4 potion de focalisation"
  },
  {
    "_type": "robe",
    "nom": "Atours du roi barbare d'inquisition \n(Paladin)",
    "unique_neerya": true,
    "force_req": 382,
    "endurance_req": 50,
    "dexterite_req": 0,
    "intelligence_req": 40,
    "sagesse_req": 362,
    "armure": 31.0,
    "prix": 0,
    "prix_detail": null,
    "informations": "+35 puissance lumière OU terre OU air (suivant l'élément dominant du personnage)  \n+50 force  \n+70 sagesse  \n+100 attaque  \n+5 toutes résistances",
    "obtention": "L'Arcaniste (Draconis Sanctum) Prix : Atours du roi barbare 6 400 000 pièces d'or 60 larmes de dragon 4 potion de focalisation"
  },
  {
    "_type": "robe",
    "nom": "Atours du roi barbare d'éxécution \n(Archer-Mage)",
    "unique_neerya": true,
    "force_req": 0,
    "endurance_req": 40,
    "dexterite_req": 417,
    "intelligence_req": 327,
    "sagesse_req": 40,
    "armure": 21.0,
    "prix": 0,
    "prix_detail": null,
    "informations": "+30 puissance feu, eau, nécro  \n+5 résistance feu, eau, air, terre, nécro  \n+50 dextérité  \n+50 intelligence  \n+100 compétence Archerie",
    "obtention": "L'Arcaniste (Draconis Sanctum) Prix : Atours du roi barbare 6 400 000 pièces d'or 60 larmes de dragon 4 potion de focalisation"
  },
  {
    "_type": "robe",
    "nom": "Atours du roi barbare de persécution \n(Anté-Paladin)",
    "unique_neerya": true,
    "force_req": 382,
    "endurance_req": 40,
    "dexterite_req": 0,
    "intelligence_req": 362,
    "sagesse_req": 40,
    "armure": 31.0,
    "prix": 0,
    "prix_detail": null,
    "informations": "+35 puissance feu OU eau OU air OU nécromancie (suivant l'élément dominant du personnage)  \n+50 force  \n +70 intelligence  \n+100 attaque  \n+5 toutes résistances",
    "obtention": "L'Arcaniste (Draconis Sanctum) Prix : Atours du roi barbare 6 400 000 pièces d'or 60 larmes de dragon 4 potion de focalisation"
  },
  {
    "_type": "robe",
    "nom": "Atours du roi barbare de rétribution \n(Archer-Prêtre)",
    "unique_neerya": true,
    "force_req": 0,
    "endurance_req": 40,
    "dexterite_req": 417,
    "intelligence_req": 40,
    "sagesse_req": 327,
    "armure": 21.0,
    "prix": 0,
    "prix_detail": null,
    "informations": "+30 puissance terre et lumière \n+50 dextérité  \n+50 sagesse  \n+100 acherie  \n+5 toutes résistances",
    "obtention": "L'Arcaniste (Draconis Sanctum) Prix : Atours du roi barbare 6 400 000 pièces d'or 60 larmes de dragon 4 potion de focalisation"
  }
]